CONTRIBUTING.md
LICENCE.txt
MANIFEST.in
PYPI.md
README.md
pyproject.toml
requirements-build.txt
requirements-duckdb.txt
requirements-lava.txt
requirements.txt
setup.py
docma/VERSION
docma/__init__.py
docma/config.py
docma/docma_core.py
docma/exceptions.py
docma/validators.py
docma/version.py
docma.egg-info/PKG-INFO
docma.egg-info/SOURCES.txt
docma.egg-info/dependency_links.txt
docma.egg-info/entry_points.txt
docma.egg-info/requires.txt
docma.egg-info/top_level.txt
docma/cli/__init__.py
docma/cli/docma.py
docma/commands/__common__.py
docma/commands/__init__.py
docma/commands/compile.py
docma/commands/html_batch.py
docma/commands/html_render.py
docma/commands/info.py
docma/commands/new.py
docma/commands/pdf_batch.py
docma/commands/pdf_render.py
docma/compilers/__common__.py
docma/compilers/__init__.py
docma/compilers/markdown.py
docma/data_providers/__common__.py
docma/data_providers/__init__.py
docma/data_providers/db.py
docma/data_providers/file.py
docma/data_providers/params.py
docma/generators/__common__.py
docma/generators/__init__.py
docma/generators/qrcode.py
docma/generators/swatch.py
docma/generators/vega.py
docma/importers/__common__.py
docma/importers/__init__.py
docma/importers/http.py
docma/importers/s3.py
docma/jinja/__init__.py
docma/jinja/core.py
docma/jinja/extensions.py
docma/jinja/resolvers.py
docma/jinja/utils.py
docma/lib/__init__.py
docma/lib/db.py
docma/lib/html.py
docma/lib/http.py
docma/lib/jsonschema.py
docma/lib/logging.py
docma/lib/metadata.py
docma/lib/misc.py
docma/lib/packager.py
docma/lib/path.py
docma/lib/plugin.py
docma/lib/query.py
docma/plugins/__init__.py
docma/plugins/format_checkers/__init__.py
docma/plugins/format_checkers/deprecated.py
docma/plugins/format_checkers/utility.py
docma/plugins/format_checkers/au/__init__.py
docma/plugins/format_checkers/au/company_ids.py
docma/plugins/format_checkers/au/industry_formats.py
docma/plugins/jinja_filters/__init__.py
docma/plugins/jinja_filters/datetime.py
docma/plugins/jinja_filters/deprecated.py
docma/plugins/jinja_filters/dollars.py
docma/plugins/jinja_filters/number.py
docma/plugins/jinja_filters/phone.py
docma/plugins/jinja_filters/utility.py
