Metadata-Version: 2.4
Name: docma
Version: 2.2.0
Summary: Document manufacturer
Home-page: https://github.com/jin-gizmo/docma
Author: Murray Andrews
License: BSD-3-Clause
Platform: macOS
Platform: Linux
Classifier: Development Status :: 5 - Production/Stable
Classifier: Environment :: Console
Classifier: Intended Audience :: Developers
Classifier: Intended Audience :: Information Technology
Classifier: Natural Language :: English
Classifier: Operating System :: MacOS
Classifier: Operating System :: POSIX :: Linux
Classifier: Programming Language :: Python :: 3 :: Only
Classifier: Topic :: Documentation
Classifier: Topic :: Text Processing
Requires-Python: >=3.11.0
License-File: LICENCE.txt
Requires-Dist: altair
Requires-Dist: babel
Requires-Dist: beautifulsoup4
Requires-Dist: boto3
Requires-Dist: cachetools
Requires-Dist: colorama
Requires-Dist: cookiecutter
Requires-Dist: duckdb
Requires-Dist: jinja2
Requires-Dist: jsonschema[format-nongpl]
Requires-Dist: markdown
Requires-Dist: pg8000
Requires-Dist: phonenumbers
Requires-Dist: pillow
Requires-Dist: pydantic
Requires-Dist: pypdf
Requires-Dist: python-dotenv
Requires-Dist: pyyaml
Requires-Dist: qrcode[pil]
Requires-Dist: referencing
Requires-Dist: requests
Requires-Dist: tqdm
Requires-Dist: vl-convert-python
Requires-Dist: weasyprint
Provides-Extra: all
Requires-Dist: duckdb; extra == "all"
Requires-Dist: jinlava>=8.0.0; extra == "all"
Provides-Extra: duckdb
Requires-Dist: duckdb; extra == "duckdb"
Provides-Extra: lava
Requires-Dist: jinlava>=8.0.0; extra == "lava"
Dynamic: author
Dynamic: classifier
Dynamic: description
Dynamic: description-content-type
Dynamic: home-page
Dynamic: license
Dynamic: license-file
Dynamic: platform
Dynamic: provides-extra
Dynamic: requires-dist
Dynamic: requires-python
Dynamic: summary
